crikit/CRIkitUI.py
crikit/__init__.py
crikit/__main__.py
crikit/cri/__init__.py
crikit/cri/error_correction.py
crikit/cri/kk.py
crikit/cri/merge_nrbs.py
crikit/cri/algorithms/__init__.py
crikit/cri/algorithms/kk.py
crikit/cri/tests/__init__.py
crikit/cri/tests/test_hilbert.py
crikit/cri/tests/test_kk.py
crikit/cri/tests/test_kk_alg.py
crikit/cri/tests/test_merge_nrbs.py
crikit/cri/tests/test_pec.py
crikit/cri/tests/test_sec.py
crikit/data/__init__.py
crikit/data/factorized.py
crikit/data/frequency.py
crikit/data/mosaic.py
crikit/data/replicate.py
crikit/data/spectra.py
crikit/data/tests/__init__.py
crikit/data/tests/test_hsi.py
crikit/data/tests/test_mosaic.py
crikit/data/tests/test_mosaic_hdf.py
crikit/data/tests/test_spectra.py
crikit/data/tests/test_spectrum.py
crikit/data/tests/~test_data_indexing.py
crikit/datasets/Chem_Conc_0.csv
crikit/datasets/Chem_Conc_1.csv
crikit/datasets/Chem_Conc_2.csv
crikit/datasets/Chem_Conc_3.csv
crikit/datasets/Chem_Conc_4.csv
crikit/datasets/Chem_Conc_5.csv
crikit/datasets/Chem_Conc_6.csv
crikit/datasets/Chem_Spec_0.csv
crikit/datasets/Chem_Spec_1.csv
crikit/datasets/Chem_Spec_2.csv
crikit/datasets/Chem_Spec_3.csv
crikit/datasets/Chem_Spec_4.csv
crikit/datasets/Chem_Spec_5.csv
crikit/datasets/Chem_Spec_6.csv
crikit/datasets/__init__.py
crikit/datasets/model.py
crikit/io/__init__.py
crikit/io/csv_nist.py
crikit/io/hdf5.py
crikit/io/macros.py
crikit/io/meta_configs.py
crikit/io/meta_process.py
crikit/io/lazy5/__init__.py
crikit/io/lazy5/alter.py
crikit/io/lazy5/config.py
crikit/io/lazy5/create.py
crikit/io/lazy5/inspect.py
crikit/io/lazy5/nonh5utils.py
crikit/io/lazy5/utils.py
crikit/io/lazy5/tests/__init__.py
crikit/io/lazy5/tests/test_alter.py
crikit/io/lazy5/tests/test_create.py
crikit/io/lazy5/tests/test_inspect.py
crikit/io/lazy5/tests/test_nonh5utils.py
crikit/io/lazy5/tests/test_ui.py
crikit/io/lazy5/tests/test_utils.py
crikit/io/lazy5/ui/QtHdfLoad.py
crikit/io/lazy5/ui/__init__.py
crikit/io/lazy5/ui/qt_HdfLoad.py
CRIkit2-0.4.4.dist-info/LICENSE.md
CRIkit2-0.4.4.dist-info/METADATA
CRIkit2-0.4.4.dist-info/WHEEL
CRIkit2-0.4.4.dist-info/entry_points.txt
CRIkit2-0.4.4.dist-info/top_level.txt
CRIkit2-0.4.4.dist-info/RECORD
