Metadata-Version: 2.1
Name: CRIkit2
Version: 0.4.4
Summary: Hyperspectral imaging (HSI) processing and analysis platform (user interface, UI)
Home-page: https://github.com/CCampJr/CRIkit2
Author: Charles H. Camp Jr.
Author-email: charles.camp@nist.gov
License: Public Domain
Classifier: Development Status :: 2 - Pre-Alpha
Classifier: Intended Audience :: Developers
Classifier: Intended Audience :: Science/Research
Classifier: Operating System :: OS Independent
Classifier: Environment :: X11 Applications :: Qt
Classifier: Programming Language :: Python :: 3 :: Only
Classifier: Programming Language :: Python :: 3.4
Classifier: Programming Language :: Python :: 3.5
Classifier: Programming Language :: Python :: 3.6
Classifier: Programming Language :: Python :: 3.7
Classifier: Topic :: Scientific/Engineering :: Visualization
License-File: LICENSE.md
Requires-Dist: numpy
Requires-Dist: matplotlib
Requires-Dist: scipy
Requires-Dist: sciplot-pyqt (>=0.2.2)
Requires-Dist: cvxopt
Requires-Dist: packaging
